setup.py
it_asset_info/__init__.py
it_asset_info/info.py
it_asset_info.egg-info/PKG-INFO
it_asset_info.egg-info/SOURCES.txt
it_asset_info.egg-info/dependency_links.txt
it_asset_info.egg-info/not-zip-safe
it_asset_info.egg-info/top_level.txt