Metadata-Version: 1.0
Name: it-asset-info
Version: 1.0
Summary: Program to fetch System information to check software compatiblity
Home-page: http://github.com/rahulrksmau/SystemInfo
Author: rahul
Author-email: rahul.k@emudhra.com
License: UNKNOWN
Platform: UNKNOWN
